<annotation>
	<folder>unlabeled</folder>
	<filename>NHL___Oct.17_2021__Dallas_Stars_-_Ottawa_Senators_65494.jpg</filename>
	<path>D:\Python\HockeyPlayerDetection\Tensorflow\workspace\images\unlabeled\NHL___Oct.17_2021__Dallas_Stars_-_Ottawa_Senators_65494.jpg</path>
	<source>
		<database>Unknown</database>
	</source>
	<size>
		<width>1280</width>
		<height>720</height>
		<depth>3</depth>
	</size>
	<segmented>0</segmented>
	<object>
		<name>hockeyplayer</name>
		<pose>Unspecified</pose>
		<truncated>0</truncated>
		<difficult>0</difficult>
		<bndbox>
			<xmin>412</xmin>
			<ymin>541</ymin>
			<xmax>501</xmax>
			<ymax>641</ymax>
		</bndbox>
	</object>
	<object>
		<name>hockeyplayer</name>
		<pose>Unspecified</pose>
		<truncated>0</truncated>
		<difficult>0</difficult>
		<bndbox>
			<xmin>925</xmin>
			<ymin>460</ymin>
			<xmax>994</xmax>
			<ymax>609</ymax>
		</bndbox>
	</object>
	<object>
		<name>hockeyplayer</name>
		<pose>Unspecified</pose>
		<truncated>0</truncated>
		<difficult>0</difficult>
		<bndbox>
			<xmin>1042</xmin>
			<ymin>520</ymin>
			<xmax>1121</xmax>
			<ymax>625</ymax>
		</bndbox>
	</object>
	<object>
		<name>hockeyplayer</name>
		<pose>Unspecified</pose>
		<truncated>0</truncated>
		<difficult>0</difficult>
		<bndbox>
			<xmin>1152</xmin>
			<ymin>170</ymin>
			<xmax>1190</xmax>
			<ymax>257</ymax>
		</bndbox>
	</object>
	<object>
		<name>referee</name>
		<pose>Unspecified</pose>
		<truncated>0</truncated>
		<difficult>0</difficult>
		<bndbox>
			<xmin>474</xmin>
			<ymin>562</ymin>
			<xmax>575</xmax>
			<ymax>642</ymax>
		</bndbox>
	</object>
	<object>
		<name>referee</name>
		<pose>Unspecified</pose>
		<truncated>0</truncated>
		<difficult>0</difficult>
		<bndbox>
			<xmin>581</xmin>
			<ymin>154</ymin>
			<xmax>615</xmax>
			<ymax>236</ymax>
		</bndbox>
	</object>
	<object>
		<name>referee</name>
		<pose>Unspecified</pose>
		<truncated>0</truncated>
		<difficult>0</difficult>
		<bndbox>
			<xmin>1190</xmin>
			<ymin>101</ymin>
			<xmax>1237</xmax>
			<ymax>174</ymax>
		</bndbox>
	</object>
</annotation>
