<annotation>
	<folder>unlabeled</folder>
	<filename>NHL__Jan.06_2022___San_Jose_Sharks_-_Buffalo_Sabres_102600.jpg</filename>
	<path>D:\Python\HockeyPlayerDetection\Tensorflow\workspace\images\unlabeled\NHL__Jan.06_2022___San_Jose_Sharks_-_Buffalo_Sabres_102600.jpg</path>
	<source>
		<database>Unknown</database>
	</source>
	<size>
		<width>1280</width>
		<height>720</height>
		<depth>3</depth>
	</size>
	<segmented>0</segmented>
	<object>
		<name>hockeyplayer</name>
		<pose>Unspecified</pose>
		<truncated>1</truncated>
		<difficult>0</difficult>
		<bndbox>
			<xmin>34</xmin>
			<ymin>585</ymin>
			<xmax>151</xmax>
			<ymax>720</ymax>
		</bndbox>
	</object>
	<object>
		<name>hockeyplayer</name>
		<pose>Unspecified</pose>
		<truncated>0</truncated>
		<difficult>0</difficult>
		<bndbox>
			<xmin>363</xmin>
			<ymin>320</ymin>
			<xmax>453</xmax>
			<ymax>469</ymax>
		</bndbox>
	</object>
	<object>
		<name>hockeyplayer</name>
		<pose>Unspecified</pose>
		<truncated>0</truncated>
		<difficult>0</difficult>
		<bndbox>
			<xmin>458</xmin>
			<ymin>157</ymin>
			<xmax>544</xmax>
			<ymax>277</ymax>
		</bndbox>
	</object>
	<object>
		<name>hockeyplayer</name>
		<pose>Unspecified</pose>
		<truncated>0</truncated>
		<difficult>0</difficult>
		<bndbox>
			<xmin>533</xmin>
			<ymin>183</ymin>
			<xmax>590</xmax>
			<ymax>286</ymax>
		</bndbox>
	</object>
	<object>
		<name>hockeyplayer</name>
		<pose>Unspecified</pose>
		<truncated>0</truncated>
		<difficult>0</difficult>
		<bndbox>
			<xmin>1033</xmin>
			<ymin>203</ymin>
			<xmax>1099</xmax>
			<ymax>336</ymax>
		</bndbox>
	</object>
</annotation>
